odoo/addons/website_hr_recruitment_legal/README.rst
odoo/addons/website_hr_recruitment_legal/__init__.py
odoo/addons/website_hr_recruitment_legal/__manifest__.py
odoo/addons/website_hr_recruitment_legal/i18n/website_hr_recruitment_legal.pot
odoo/addons/website_hr_recruitment_legal/readme/CONTRIBUTORS.rst
odoo/addons/website_hr_recruitment_legal/readme/DESCRIPTION.rst
odoo/addons/website_hr_recruitment_legal/readme/USAGE.rst
odoo/addons/website_hr_recruitment_legal/static/description/icon.png
odoo/addons/website_hr_recruitment_legal/static/description/index.html
odoo/addons/website_hr_recruitment_legal/templates/apply.xml
odoo11_addon_website_hr_recruitment_legal-11.0.1.0.0.99.dev7.dist-info/METADATA
odoo11_addon_website_hr_recruitment_legal-11.0.1.0.0.99.dev7.dist-info/WHEEL
odoo11_addon_website_hr_recruitment_legal-11.0.1.0.0.99.dev7.dist-info/top_level.txt
odoo11_addon_website_hr_recruitment_legal-11.0.1.0.0.99.dev7.dist-info/RECORD
