Metadata-Version: 2.1
Name: odoo11-addon-website-hr-recruitment-legal
Version: 11.0.1.0.0.99.dev7
Summary: People must accept legal terms to apply for a job
Home-page: https://github.com/OCA/website
Author: Tecnativa, Odoo Community Association (OCA)
Author-email: support@odoo-community.org
License: AGPL-3
Platform: UNKNOWN
Classifier: Programming Language :: Python
Classifier: Framework :: Odoo
Classifier: Framework :: Odoo :: 11.0
Classifier: License :: OSI Approved :: GNU Affero General Public License v3
Classifier: Development Status :: 3 - Alpha
Requires-Python: >=2.7, !=3.0.*, !=3.1.*, !=3.2.*, !=3.3.*, !=3.4.*
Requires-Dist: odoo11-addon-website-legal-page
Requires-Dist: odoo <11.1dev,>=11.0a
